clickgen/__init__.py
clickgen/__init__.pyi
clickgen/configparser.py
clickgen/configparser.pyi
clickgen/cursors.py
clickgen/cursors.pyi
clickgen/py.typed
clickgen/libs/__init__.py
clickgen/libs/__init__.pyi
clickgen/libs/colors.py
clickgen/libs/colors.pyi
clickgen/packer/__init__.py
clickgen/packer/__init__.pyi
clickgen/packer/windows.py
clickgen/packer/windows.pyi
clickgen/packer/x11.py
clickgen/packer/x11.pyi
clickgen/parser/__init__.py
clickgen/parser/__init__.pyi
clickgen/parser/base.py
clickgen/parser/base.pyi
clickgen/parser/png.py
clickgen/parser/png.pyi
clickgen/scripts/__init__.py
clickgen/scripts/__init__.pyi
clickgen/scripts/clickgen.py
clickgen/scripts/clickgen.pyi
clickgen/scripts/ctgen.py
clickgen/scripts/ctgen.pyi
clickgen/writer/__init__.py
clickgen/writer/__init__.pyi
clickgen/writer/windows.py
clickgen/writer/windows.pyi
clickgen/writer/x11.py
clickgen/writer/x11.pyi
clickgen-2.2.5.dist-info/LICENSE
clickgen-2.2.5.dist-info/METADATA
clickgen-2.2.5.dist-info/WHEEL
clickgen-2.2.5.dist-info/entry_points.txt
clickgen-2.2.5.dist-info/top_level.txt
clickgen-2.2.5.dist-info/RECORD
