Metadata-Version: 2.1
Name: clickgen
Version: 2.2.5
Summary: The hassle-free cursor building toolbox.
Home-page: https://github.com/ful1e5/clickgen
Author: Abdulkaiz Khatri
Author-email: kaizmandhu@gmail.com
Project-URL: Source, https://github.com/ful1e5/clickgen
Project-URL: Download, https://pypi.org/project/clickgen/#files
Project-URL: Bug Tracker, https://github.com/ful1e5/clickgen/issues
Project-URL: Changelog, https://github.com/ful1e5/clickgen/blob/main/CHANGELOG.md
Project-URL: Funding, https://github.com/sponsors/ful1e5
Project-URL: Twitter, https://twitter.com/ful1e5
Keywords: cursor,xcursor,windows,linux
Classifier: Development Status :: 6 - Mature
Classifier: License :: OSI Approved :: MIT License
Classifier: Programming Language :: Python :: 3 :: Only
Classifier: Programming Language :: Python :: 3
Classifier: Programming Language :: Python :: 3.7
Classifier: Programming Language :: Python :: 3.8
Classifier: Programming Language :: Python :: 3.9
Classifier: Programming Language :: Python :: 3.10
Classifier: Programming Language :: Python :: 3.11
Classifier: Programming Language :: Python :: 3.12
Classifier: Topic :: Multimedia :: Graphics
Classifier: Topic :: System :: Operating System
Classifier: Topic :: Scientific/Engineering :: Image Processing
Classifier: Operating System :: OS Independent
Classifier: Typing :: Typed
Requires-Python: >=3.7.5
License-File: LICENSE
Requires-Dist: Pillow >=8.1.1
Requires-Dist: PyYaml >=6.0.1
Requires-Dist: attrs >=15.0.0
Requires-Dist: numpy >=1.21.6
Requires-Dist: toml >=0.10.2
Provides-Extra: build
Requires-Dist: build >=0.10.0 ; extra == 'build'
Provides-Extra: test
Requires-Dist: flake8 >=4.0.1 ; extra == 'test'
Requires-Dist: mypy >=0.982 ; extra == 'test'
Requires-Dist: pytest-cov >=3.0.0 ; extra == 'test'
Requires-Dist: pytest >=7.0.1 ; extra == 'test'
Requires-Dist: tox >=3.25.0 ; extra == 'test'
